labthings/__init__.py
labthings/actions/__init__.py
labthings/actions/pool.py
labthings/actions/thread.py
labthings/apispec/__init__.py
labthings/apispec/plugins.py
labthings/apispec/utilities.py
labthings/default_views/__init__.py
labthings/default_views/actions.py
labthings/default_views/docs/__init__.py
labthings/default_views/docs/static/favicon-16x16.png
labthings/default_views/docs/static/favicon-32x32.png
labthings/default_views/docs/static/index.html
labthings/default_views/docs/static/oauth2-redirect.html
labthings/default_views/docs/static/swagger-ui-bundle.js
labthings/default_views/docs/static/swagger-ui-bundle.js.map
labthings/default_views/docs/static/swagger-ui-standalone-preset.js
labthings/default_views/docs/static/swagger-ui-standalone-preset.js.map
labthings/default_views/docs/static/swagger-ui.css
labthings/default_views/docs/static/swagger-ui.css.map
labthings/default_views/docs/static/swagger-ui.js
labthings/default_views/docs/static/swagger-ui.js.map
labthings/default_views/docs/templates/swagger-ui.html
labthings/default_views/events.py
labthings/default_views/extensions.py
labthings/default_views/root.py
labthings/deque.py
labthings/example_components/__init__.py
labthings/example_components/spectrometer.py
labthings/extensions.py
labthings/fields.py
labthings/find.py
labthings/httperrorhandler.py
labthings/json/__init__.py
labthings/json/encoder.py
labthings/json/marshmallow_jsonschema/LICENSE
labthings/json/marshmallow_jsonschema/README
labthings/json/marshmallow_jsonschema/__init__.py
labthings/json/marshmallow_jsonschema/base.py
labthings/json/marshmallow_jsonschema/exceptions.py
labthings/json/marshmallow_jsonschema/validation.py
labthings/json/schemas.py
labthings/labthing.py
labthings/logging.py
labthings/marshalling/__init__.py
labthings/marshalling/args.py
labthings/marshalling/marshalling.py
labthings/monkey.py
labthings/names.py
labthings/py.typed
labthings/quick.py
labthings/representations.py
labthings/responses.py
labthings-1.3.1.dist-info/LICENSE
labthings-1.3.1.dist-info/WHEEL
labthings-1.3.1.dist-info/METADATA
labthings-1.3.1.dist-info/RECORD
