Metadata-Version: 2.1
Name: labthings
Version: 1.3.1
Summary: Python implementation of LabThings, based on the Flask microframework
Home-page: https://github.com/labthings/python-labthings/
Author: Joel Collins
Author-email: joel@jtcollins.net
Requires-Python: >=3.6,<4.0
Classifier: Programming Language :: Python :: 3
Classifier: Programming Language :: Python :: 3.6
Classifier: Programming Language :: Python :: 3.7
Classifier: Programming Language :: Python :: 3.8
Classifier: Programming Language :: Python :: 3.9
Classifier: Topic :: Internet :: WWW/HTTP :: WSGI
Classifier: Topic :: Software Development :: Libraries :: Application Frameworks
Classifier: Topic :: System :: Hardware
Requires-Dist: Flask (>=1.1.1,<2.0.0)
Requires-Dist: apispec[yaml,validation] (>=3.2,<5.0)
Requires-Dist: apispec_webframeworks (>=0.5.2,<0.6.0)
Requires-Dist: flask-cors (>=3.0.8,<4.0.0)
Requires-Dist: marshmallow (>=3.4.0,<4.0.0)
Requires-Dist: webargs (>=6,<9)
Requires-Dist: zeroconf (>=0.24.5,<0.34.0)
Project-URL: Repository, https://github.com/labthings/python-labthings/
